{"config":{"output_file":null,"full_docs":false,"pub_only":true,"reachable_only":true,"distro_crate":false,"signatures":false,"borrow_data":false},"version":"0.19.0","compilation":{"directory":"/Users/icaroferre/.cargo/registry/src/github.com-1ecc6299db9ec823/num-0.1.42","program":"/Users/icaroferre/.rustup/toolchains/stable-x86_64-apple-darwin/bin/rls","arguments":["--crate-name","num","/Users/icaroferre/.cargo/registry/src/github.com-1ecc6299db9ec823/num-0.1.42/src/lib.rs","--json=diagnostic-rendered-ansi","--crate-type","lib","--emit=dep-info,metadata","-C","debuginfo=2","--cfg","feature=\"bigint\"","--cfg","feature=\"complex\"","--cfg","feature=\"default\"","--cfg","feature=\"num-bigint\"","--cfg","feature=\"num-complex\"","--cfg","feature=\"num-rational\"","--cfg","feature=\"rational\"","--cfg","feature=\"rustc-serialize\"","-C","metadata=b263deaa2ba14547","-C","extra-filename=-b263deaa2ba14547","--out-dir","/Users/icaroferre/Dropbox/Work/GitHub/AudioHit/code/target/rls/debug/deps","-L","dependency=/Users/icaroferre/Dropbox/Work/GitHub/AudioHit/code/target/rls/debug/deps","--extern","num_bigint=/Users/icaroferre/Dropbox/Work/GitHub/AudioHit/code/target/rls/debug/deps/libnum_bigint-cfc6f0d412efcbf4.rmeta","--extern","num_complex=/Users/icaroferre/Dropbox/Work/GitHub/AudioHit/code/target/rls/debug/deps/libnum_complex-43c957b0845fd8a5.rmeta","--extern","num_integer=/Users/icaroferre/Dropbox/Work/GitHub/AudioHit/code/target/rls/debug/deps/libnum_integer-ddfcac9a009914c9.rmeta","--extern","num_iter=/Users/icaroferre/Dropbox/Work/GitHub/AudioHit/code/target/rls/debug/deps/libnum_iter-2e9fc3a167406cac.rmeta","--extern","num_rational=/Users/icaroferre/Dropbox/Work/GitHub/AudioHit/code/target/rls/debug/deps/libnum_rational-1e92889814aa06d1.rmeta","--extern","num_traits=/Users/icaroferre/Dropbox/Work/GitHub/AudioHit/code/target/rls/debug/deps/libnum_traits-792008c6cad787f6.rmeta","--cap-lints","allow","--error-format=json","--sysroot","/Users/icaroferre/.rustup/toolchains/stable-x86_64-apple-darwin"],"output":"/Users/icaroferre/Dropbox/Work/GitHub/AudioHit/code/target/rls/debug/deps/libnum-b263deaa2ba14547.rmeta"},"prelude":{"crate_id":{"name":"num","disambiguator":[12243993155964613155,13101777113854849608]},"crate_root":"/Users/icaroferre/.cargo/registry/src/github.com-1ecc6299db9ec823/num-0.1.42/src","external_crates":[{"file_name":"/Users/icaroferre/.cargo/registry/src/github.com-1ecc6299db9ec823/num-0.1.42/src/lib.rs","num":1,"id":{"name":"std","disambiguator":[12036975874919608542,5263022788913298406]}},{"file_name":"/Users/icaroferre/.cargo/registry/src/github.com-1ecc6299db9ec823/num-0.1.42/src/lib.rs","num":2,"id":{"name":"core","disambiguator":[12685141629749505872,14384861886608688020]}},{"file_name":"/Users/icaroferre/.cargo/registry/src/github.com-1ecc6299db9ec823/num-0.1.42/src/lib.rs","num":3,"id":{"name":"compiler_builtins","disambiguator":[12340268601481677029,141089188236804857]}},{"file_name":"/Users/icaroferre/.cargo/registry/src/github.com-1ecc6299db9ec823/num-0.1.42/src/lib.rs","num":4,"id":{"name":"rustc_std_workspace_core","disambiguator":[15672008270625504507,2674350736569664385]}},{"file_name":"/Users/icaroferre/.cargo/registry/src/github.com-1ecc6299db9ec823/num-0.1.42/src/lib.rs","num":5,"id":{"name":"alloc","disambiguator":[8066833728442541494,18441909558183702075]}},{"file_name":"/Users/icaroferre/.cargo/registry/src/github.com-1ecc6299db9ec823/num-0.1.42/src/lib.rs","num":6,"id":{"name":"libc","disambiguator":[18762513522875297,12336434793998892008]}},{"file_name":"/Users/icaroferre/.cargo/registry/src/github.com-1ecc6299db9ec823/num-0.1.42/src/lib.rs","num":7,"id":{"name":"unwind","disambiguator":[6386993580917896473,10528920155300651342]}},{"file_name":"/Users/icaroferre/.cargo/registry/src/github.com-1ecc6299db9ec823/num-0.1.42/src/lib.rs","num":8,"id":{"name":"cfg_if","disambiguator":[63588754982269101,9431025315804350196]}},{"file_name":"/Users/icaroferre/.cargo/registry/src/github.com-1ecc6299db9ec823/num-0.1.42/src/lib.rs","num":9,"id":{"name":"backtrace","disambiguator":[6693364396395125059,14894688029700829747]}},{"file_name":"/Users/icaroferre/.cargo/registry/src/github.com-1ecc6299db9ec823/num-0.1.42/src/lib.rs","num":10,"id":{"name":"rustc_demangle","disambiguator":[16603275402718143122,14067629355158943163]}},{"file_name":"/Users/icaroferre/.cargo/registry/src/github.com-1ecc6299db9ec823/num-0.1.42/src/lib.rs","num":11,"id":{"name":"backtrace_sys","disambiguator":[10587581080033021223,10965447884951720582]}},{"file_name":"/Users/icaroferre/.cargo/registry/src/github.com-1ecc6299db9ec823/num-0.1.42/src/lib.rs","num":12,"id":{"name":"hashbrown","disambiguator":[4572683954975939282,9115057533031414731]}},{"file_name":"/Users/icaroferre/.cargo/registry/src/github.com-1ecc6299db9ec823/num-0.1.42/src/lib.rs","num":13,"id":{"name":"rustc_std_workspace_alloc","disambiguator":[12668818391670187517,11018761801619609470]}},{"file_name":"/Users/icaroferre/.cargo/registry/src/github.com-1ecc6299db9ec823/num-0.1.42/src/lib.rs","num":14,"id":{"name":"panic_unwind","disambiguator":[13970895335240303563,1394509620320337557]}},{"file_name":"/Users/icaroferre/.cargo/registry/src/github.com-1ecc6299db9ec823/num-0.1.42/src/lib.rs","num":15,"id":{"name":"num_traits","disambiguator":[14789538818268615845,18072746685886985669]}},{"file_name":"/Users/icaroferre/.cargo/registry/src/github.com-1ecc6299db9ec823/num-0.1.42/src/lib.rs","num":16,"id":{"name":"num_integer","disambiguator":[17634200879079014880,14674970951420522940]}},{"file_name":"/Users/icaroferre/.cargo/registry/src/github.com-1ecc6299db9ec823/num-0.1.42/src/lib.rs","num":17,"id":{"name":"num_iter","disambiguator":[3828906837853572525,6483067104730599608]}},{"file_name":"/Users/icaroferre/.cargo/registry/src/github.com-1ecc6299db9ec823/num-0.1.42/src/lib.rs","num":18,"id":{"name":"num_complex","disambiguator":[12591739690526031866,3869244916472408377]}},{"file_name":"/Users/icaroferre/.cargo/registry/src/github.com-1ecc6299db9ec823/num-0.1.42/src/lib.rs","num":19,"id":{"name":"rustc_serialize","disambiguator":[6358982076254951874,10943599007808113548]}},{"file_name":"/Users/icaroferre/.cargo/registry/src/github.com-1ecc6299db9ec823/num-0.1.42/src/lib.rs","num":20,"id":{"name":"num_bigint","disambiguator":[11103561227546803173,4970388597717771817]}},{"file_name":"/Users/icaroferre/.cargo/registry/src/github.com-1ecc6299db9ec823/num-0.1.42/src/lib.rs","num":21,"id":{"name":"rand","disambiguator":[15268491522432239319,15142043230507969412]}},{"file_name":"/Users/icaroferre/.cargo/registry/src/github.com-1ecc6299db9ec823/num-0.1.42/src/lib.rs","num":22,"id":{"name":"libc","disambiguator":[12019967524813203085,2241512072167285732]}},{"file_name":"/Users/icaroferre/.cargo/registry/src/github.com-1ecc6299db9ec823/num-0.1.42/src/lib.rs","num":23,"id":{"name":"num_rational","disambiguator":[11866593175137493292,13149021036959601434]}}],"span":{"file_name":"/Users/icaroferre/.cargo/registry/src/github.com-1ecc6299db9ec823/num-0.1.42/src/lib.rs","byte_start":472,"byte_end":3381,"line_start":11,"line_end":113,"column_start":1,"column_end":2}},"imports":[{"kind":"Use","ref_id":{"krate":20,"index":1887},"span":{"file_name":"/Users/icaroferre/.cargo/registry/src/github.com-1ecc6299db9ec823/num-0.1.42/src/lib.rs","byte_start":2326,"byte_end":2332,"line_start":73,"line_end":73,"column_start":22,"column_end":28},"alias_span":null,"name":"BigInt","value":"","parent":{"krate":0,"index":0}},{"kind":"Use","ref_id":{"krate":20,"index":858},"span":{"file_name":"/Users/icaroferre/.cargo/registry/src/github.com-1ecc6299db9ec823/num-0.1.42/src/lib.rs","byte_start":2334,"byte_end":2341,"line_start":73,"line_end":73,"column_start":30,"column_end":37},"alias_span":null,"name":"BigUint","value":"","parent":{"krate":0,"index":0}},{"kind":"Use","ref_id":{"krate":23,"index":40},"span":{"file_name":"/Users/icaroferre/.cargo/registry/src/github.com-1ecc6299db9ec823/num-0.1.42/src/lib.rs","byte_start":2399,"byte_end":2407,"line_start":75,"line_end":75,"column_start":23,"column_end":31},"alias_span":null,"name":"Rational","value":"","parent":{"krate":0,"index":0}},{"kind":"Use","ref_id":{"krate":23,"index":43},"span":{"file_name":"/Users/icaroferre/.cargo/registry/src/github.com-1ecc6299db9ec823/num-0.1.42/src/lib.rs","byte_start":2491,"byte_end":2502,"line_start":77,"line_end":77,"column_start":23,"column_end":34},"alias_span":null,"name":"BigRational","value":"","parent":{"krate":0,"index":0}},{"kind":"Use","ref_id":{"krate":18,"index":223},"span":{"file_name":"/Users/icaroferre/.cargo/registry/src/github.com-1ecc6299db9ec823/num-0.1.42/src/lib.rs","byte_start":2557,"byte_end":2564,"line_start":79,"line_end":79,"column_start":22,"column_end":29},"alias_span":null,"name":"Complex","value":"","parent":{"krate":0,"index":0}},{"kind":"Use","ref_id":{"krate":16,"index":11},"span":{"file_name":"/Users/icaroferre/.cargo/registry/src/github.com-1ecc6299db9ec823/num-0.1.42/src/lib.rs","byte_start":2587,"byte_end":2594,"line_start":80,"line_end":80,"column_start":22,"column_end":29},"alias_span":null,"name":"Integer","value":"","parent":{"krate":0,"index":0}},{"kind":"Use","ref_id":{"krate":17,"index":17},"span":{"file_name":"/Users/icaroferre/.cargo/registry/src/github.com-1ecc6299db9ec823/num-0.1.42/src/lib.rs","byte_start":2615,"byte_end":2620,"line_start":81,"line_end":81,"column_start":20,"column_end":25},"alias_span":null,"name":"range","value":"","parent":{"krate":0,"index":0}},{"kind":"Use","ref_id":{"krate":17,"index":29},"span":{"file_name":"/Users/icaroferre/.cargo/registry/src/github.com-1ecc6299db9ec823/num-0.1.42/src/lib.rs","byte_start":2622,"byte_end":2637,"line_start":81,"line_end":81,"column_start":27,"column_end":42},"alias_span":null,"name":"range_inclusive","value":"","parent":{"krate":0,"index":0}},{"kind":"Use","ref_id":{"krate":17,"index":39},"span":{"file_name":"/Users/icaroferre/.cargo/registry/src/github.com-1ecc6299db9ec823/num-0.1.42/src/lib.rs","byte_start":2639,"byte_end":2649,"line_start":81,"line_end":81,"column_start":44,"column_end":54},"alias_span":null,"name":"range_step","value":"","parent":{"krate":0,"index":0}},{"kind":"Use","ref_id":{"krate":17,"index":45},"span":{"file_name":"/Users/icaroferre/.cargo/registry/src/github.com-1ecc6299db9ec823/num-0.1.42/src/lib.rs","byte_start":2651,"byte_end":2671,"line_start":81,"line_end":81,"column_start":56,"column_end":76},"alias_span":null,"name":"range_step_inclusive","value":"","parent":{"krate":0,"index":0}},{"kind":"Use","ref_id":{"krate":15,"index":552},"span":{"file_name":"/Users/icaroferre/.cargo/registry/src/github.com-1ecc6299db9ec823/num-0.1.42/src/lib.rs","byte_start":2695,"byte_end":2698,"line_start":82,"line_end":82,"column_start":22,"column_end":25},"alias_span":null,"name":"Num","value":"","parent":{"krate":0,"index":0}},{"kind":"Use","ref_id":{"krate":15,"index":70},"span":{"file_name":"/Users/icaroferre/.cargo/registry/src/github.com-1ecc6299db9ec823/num-0.1.42/src/lib.rs","byte_start":2700,"byte_end":2704,"line_start":82,"line_end":82,"column_start":27,"column_end":31},"alias_span":null,"name":"Zero","value":"","parent":{"krate":0,"index":0}},{"kind":"Use","ref_id":{"krate":15,"index":78},"span":{"file_name":"/Users/icaroferre/.cargo/registry/src/github.com-1ecc6299db9ec823/num-0.1.42/src/lib.rs","byte_start":2706,"byte_end":2709,"line_start":82,"line_end":82,"column_start":33,"column_end":36},"alias_span":null,"name":"One","value":"","parent":{"krate":0,"index":0}},{"kind":"Use","ref_id":{"krate":15,"index":94},"span":{"file_name":"/Users/icaroferre/.cargo/registry/src/github.com-1ecc6299db9ec823/num-0.1.42/src/lib.rs","byte_start":2711,"byte_end":2717,"line_start":82,"line_end":82,"column_start":38,"column_end":44},"alias_span":null,"name":"Signed","value":"","parent":{"krate":0,"index":0}},{"kind":"Use","ref_id":{"krate":15,"index":115},"span":{"file_name":"/Users/icaroferre/.cargo/registry/src/github.com-1ecc6299db9ec823/num-0.1.42/src/lib.rs","byte_start":2719,"byte_end":2727,"line_start":82,"line_end":82,"column_start":46,"column_end":54},"alias_span":null,"name":"Unsigned","value":"","parent":{"krate":0,"index":0}},{"kind":"Use","ref_id":{"krate":15,"index":235},"span":{"file_name":"/Users/icaroferre/.cargo/registry/src/github.com-1ecc6299db9ec823/num-0.1.42/src/lib.rs","byte_start":2729,"byte_end":2736,"line_start":82,"line_end":82,"column_start":56,"column_end":63},"alias_span":null,"name":"Bounded","value":"","parent":{"krate":0,"index":0}},{"kind":"Use","ref_id":{"krate":15,"index":87},"span":{"file_name":"/Users/icaroferre/.cargo/registry/src/github.com-1ecc6299db9ec823/num-0.1.42/src/lib.rs","byte_start":2759,"byte_end":2762,"line_start":83,"line_end":83,"column_start":22,"column_end":25},"alias_span":null,"name":"one","value":"","parent":{"krate":0,"index":0}},{"kind":"Use","ref_id":{"krate":15,"index":85},"span":{"file_name":"/Users/icaroferre/.cargo/registry/src/github.com-1ecc6299db9ec823/num-0.1.42/src/lib.rs","byte_start":2764,"byte_end":2768,"line_start":83,"line_end":83,"column_start":27,"column_end":31},"alias_span":null,"name":"zero","value":"","parent":{"krate":0,"index":0}},{"kind":"Use","ref_id":{"krate":15,"index":109},"span":{"file_name":"/Users/icaroferre/.cargo/registry/src/github.com-1ecc6299db9ec823/num-0.1.42/src/lib.rs","byte_start":2770,"byte_end":2773,"line_start":83,"line_end":83,"column_start":33,"column_end":36},"alias_span":null,"name":"abs","value":"","parent":{"krate":0,"index":0}},{"kind":"Use","ref_id":{"krate":15,"index":111},"span":{"file_name":"/Users/icaroferre/.cargo/registry/src/github.com-1ecc6299db9ec823/num-0.1.42/src/lib.rs","byte_start":2775,"byte_end":2782,"line_start":83,"line_end":83,"column_start":38,"column_end":45},"alias_span":null,"name":"abs_sub","value":"","parent":{"krate":0,"index":0}},{"kind":"Use","ref_id":{"krate":15,"index":113},"span":{"file_name":"/Users/icaroferre/.cargo/registry/src/github.com-1ecc6299db9ec823/num-0.1.42/src/lib.rs","byte_start":2784,"byte_end":2790,"line_start":83,"line_end":83,"column_start":47,"column_end":53},"alias_span":null,"name":"signum","value":"","parent":{"krate":0,"index":0}},{"kind":"Use","ref_id":{"krate":15,"index":121},"span":{"file_name":"/Users/icaroferre/.cargo/registry/src/github.com-1ecc6299db9ec823/num-0.1.42/src/lib.rs","byte_start":2813,"byte_end":2823,"line_start":84,"line_end":84,"column_start":22,"column_end":32},"alias_span":null,"name":"Saturating","value":"","parent":{"krate":0,"index":0}},{"kind":"Use","ref_id":{"krate":15,"index":134},"span":{"file_name":"/Users/icaroferre/.cargo/registry/src/github.com-1ecc6299db9ec823/num-0.1.42/src/lib.rs","byte_start":2825,"byte_end":2835,"line_start":84,"line_end":84,"column_start":34,"column_end":44},"alias_span":null,"name":"CheckedAdd","value":"","parent":{"krate":0,"index":0}},{"kind":"Use","ref_id":{"krate":15,"index":137},"span":{"file_name":"/Users/icaroferre/.cargo/registry/src/github.com-1ecc6299db9ec823/num-0.1.42/src/lib.rs","byte_start":2837,"byte_end":2847,"line_start":84,"line_end":84,"column_start":46,"column_end":56},"alias_span":null,"name":"CheckedSub","value":"","parent":{"krate":0,"index":0}},{"kind":"Use","ref_id":{"krate":15,"index":139},"span":{"file_name":"/Users/icaroferre/.cargo/registry/src/github.com-1ecc6299db9ec823/num-0.1.42/src/lib.rs","byte_start":2849,"byte_end":2859,"line_start":84,"line_end":84,"column_start":58,"column_end":68},"alias_span":null,"name":"CheckedMul","value":"","parent":{"krate":0,"index":0}},{"kind":"Use","ref_id":{"krate":15,"index":141},"span":{"file_name":"/Users/icaroferre/.cargo/registry/src/github.com-1ecc6299db9ec823/num-0.1.42/src/lib.rs","byte_start":2861,"byte_end":2871,"line_start":84,"line_end":84,"column_start":70,"column_end":80},"alias_span":null,"name":"CheckedDiv","value":"","parent":{"krate":0,"index":0}},{"kind":"Use","ref_id":{"krate":15,"index":516},"span":{"file_name":"/Users/icaroferre/.cargo/registry/src/github.com-1ecc6299db9ec823/num-0.1.42/src/lib.rs","byte_start":2894,"byte_end":2901,"line_start":85,"line_end":85,"column_start":22,"column_end":29},"alias_span":null,"name":"PrimInt","value":"","parent":{"krate":0,"index":0}},{"kind":"Use","ref_id":{"krate":15,"index":290},"span":{"file_name":"/Users/icaroferre/.cargo/registry/src/github.com-1ecc6299db9ec823/num-0.1.42/src/lib.rs","byte_start":2903,"byte_end":2908,"line_start":85,"line_end":85,"column_start":31,"column_end":36},"alias_span":null,"name":"Float","value":"","parent":{"krate":0,"index":0}},{"kind":"Use","ref_id":{"krate":15,"index":430},"span":{"file_name":"/Users/icaroferre/.cargo/registry/src/github.com-1ecc6299db9ec823/num-0.1.42/src/lib.rs","byte_start":2910,"byte_end":2921,"line_start":85,"line_end":85,"column_start":38,"column_end":49},"alias_span":null,"name":"ToPrimitive","value":"","parent":{"krate":0,"index":0}},{"kind":"Use","ref_id":{"krate":15,"index":465},"span":{"file_name":"/Users/icaroferre/.cargo/registry/src/github.com-1ecc6299db9ec823/num-0.1.42/src/lib.rs","byte_start":2923,"byte_end":2936,"line_start":85,"line_end":85,"column_start":51,"column_end":64},"alias_span":null,"name":"FromPrimitive","value":"","parent":{"krate":0,"index":0}},{"kind":"Use","ref_id":{"krate":15,"index":490},"span":{"file_name":"/Users/icaroferre/.cargo/registry/src/github.com-1ecc6299db9ec823/num-0.1.42/src/lib.rs","byte_start":2938,"byte_end":2945,"line_start":85,"line_end":85,"column_start":66,"column_end":73},"alias_span":null,"name":"NumCast","value":"","parent":{"krate":0,"index":0}},{"kind":"Use","ref_id":{"krate":15,"index":408},"span":{"file_name":"/Users/icaroferre/.cargo/registry/src/github.com-1ecc6299db9ec823/num-0.1.42/src/lib.rs","byte_start":2947,"byte_end":2951,"line_start":85,"line_end":85,"column_start":75,"column_end":79},"alias_span":null,"name":"cast","value":"","parent":{"krate":0,"index":0}},{"kind":"Use","ref_id":{"krate":15,"index":534},"span":{"file_name":"/Users/icaroferre/.cargo/registry/src/github.com-1ecc6299db9ec823/num-0.1.42/src/lib.rs","byte_start":2974,"byte_end":2977,"line_start":86,"line_end":86,"column_start":22,"column_end":25},"alias_span":null,"name":"pow","value":"","parent":{"krate":0,"index":0}},{"kind":"Use","ref_id":{"krate":15,"index":549},"span":{"file_name":"/Users/icaroferre/.cargo/registry/src/github.com-1ecc6299db9ec823/num-0.1.42/src/lib.rs","byte_start":2979,"byte_end":2990,"line_start":86,"line_end":86,"column_start":27,"column_end":38},"alias_span":null,"name":"checked_pow","value":"","parent":{"krate":0,"index":0}},{"kind":"Use","ref_id":{"krate":15,"index":595},"span":{"file_name":"/Users/icaroferre/.cargo/registry/src/github.com-1ecc6299db9ec823/num-0.1.42/src/lib.rs","byte_start":2992,"byte_end":2997,"line_start":86,"line_end":86,"column_start":40,"column_end":45},"alias_span":null,"name":"clamp","value":"","parent":{"krate":0,"index":0}},{"kind":"GlobUse","ref_id":null,"span":{"file_name":"/Users/icaroferre/.cargo/registry/src/github.com-1ecc6299db9ec823/num-0.1.42/src/lib.rs","byte_start":3073,"byte_end":3074,"line_start":90,"line_end":90,"column_start":25,"column_end":26},"alias_span":null,"name":"*","value":"","parent":{"krate":0,"index":47}},{"kind":"GlobUse","ref_id":null,"span":{"file_name":"/Users/icaroferre/.cargo/registry/src/github.com-1ecc6299db9ec823/num-0.1.42/src/lib.rs","byte_start":3073,"byte_end":3074,"line_start":90,"line_end":90,"column_start":25,"column_end":26},"alias_span":null,"name":"*","value":"","parent":{"krate":0,"index":49}},{"kind":"GlobUse","ref_id":null,"span":{"file_name":"/Users/icaroferre/.cargo/registry/src/github.com-1ecc6299db9ec823/num-0.1.42/src/lib.rs","byte_start":3073,"byte_end":3074,"line_start":90,"line_end":90,"column_start":25,"column_end":26},"alias_span":null,"name":"*","value":"","parent":{"krate":0,"index":51}},{"kind":"GlobUse","ref_id":null,"span":{"file_name":"/Users/icaroferre/.cargo/registry/src/github.com-1ecc6299db9ec823/num-0.1.42/src/lib.rs","byte_start":3073,"byte_end":3074,"line_start":90,"line_end":90,"column_start":25,"column_end":26},"alias_span":null,"name":"*","value":"","parent":{"krate":0,"index":53}},{"kind":"GlobUse","ref_id":null,"span":{"file_name":"/Users/icaroferre/.cargo/registry/src/github.com-1ecc6299db9ec823/num-0.1.42/src/lib.rs","byte_start":3073,"byte_end":3074,"line_start":90,"line_end":90,"column_start":25,"column_end":26},"alias_span":null,"name":"*","value":"","parent":{"krate":0,"index":55}},{"kind":"GlobUse","ref_id":null,"span":{"file_name":"/Users/icaroferre/.cargo/registry/src/github.com-1ecc6299db9ec823/num-0.1.42/src/lib.rs","byte_start":3073,"byte_end":3074,"line_start":90,"line_end":90,"column_start":25,"column_end":26},"alias_span":null,"name":"*","value":"","parent":{"krate":0,"index":57}}],"defs":[{"kind":"Mod","id":{"krate":0,"index":0},"span":{"file_name":"/Users/icaroferre/.cargo/registry/src/github.com-1ecc6299db9ec823/num-0.1.42/src/lib.rs","byte_start":472,"byte_end":3381,"line_start":11,"line_end":113,"column_start":1,"column_end":2},"name":"","qualname":"::","value":"/Users/icaroferre/.cargo/registry/src/github.com-1ecc6299db9ec823/num-0.1.42/src/lib.rs","parent":null,"children":[{"krate":0,"index":1},{"krate":0,"index":2},{"krate":0,"index":3},{"krate":0,"index":4},{"krate":0,"index":5},{"krate":0,"index":6},{"krate":0,"index":7},{"krate":0,"index":8},{"krate":0,"index":9},{"krate":0,"index":12},{"krate":0,"index":13},{"krate":0,"index":14},{"krate":0,"index":15},{"krate":0,"index":16},{"krate":0,"index":21},{"krate":0,"index":47},{"krate":0,"index":49},{"krate":0,"index":51},{"krate":0,"index":53},{"krate":0,"index":55},{"krate":0,"index":57}],"decl_id":null,"docs":" A collection of numeric types and traits for Rust.","sig":null,"attributes":[{"value":"! A collection of numeric types and traits for Rust.","span":{"file_name":"/Users/icaroferre/.cargo/registry/src/github.com-1ecc6299db9ec823/num-0.1.42/src/lib.rs","byte_start":472,"byte_end":526,"line_start":11,"line_end":11,"column_start":1,"column_end":55}},{"value":"!","span":{"file_name":"/Users/icaroferre/.cargo/registry/src/github.com-1ecc6299db9ec823/num-0.1.42/src/lib.rs","byte_start":527,"byte_end":530,"line_start":12,"line_end":12,"column_start":1,"column_end":4}},{"value":"! This includes new types for big integers, rationals, and complex numbers,","span":{"file_name":"/Users/icaroferre/.cargo/registry/src/github.com-1ecc6299db9ec823/num-0.1.42/src/lib.rs","byte_start":531,"byte_end":608,"line_start":13,"line_end":13,"column_start":1,"column_end":78}},{"value":"! new traits for generic programming on numeric properties like `Integer`,","span":{"file_name":"/Users/icaroferre/.cargo/registry/src/github.com-1ecc6299db9ec823/num-0.1.42/src/lib.rs","byte_start":609,"byte_end":685,"line_start":14,"line_end":14,"column_start":1,"column_end":77}},{"value":"! and generic range iterators.","span":{"file_name":"/Users/icaroferre/.cargo/registry/src/github.com-1ecc6299db9ec823/num-0.1.42/src/lib.rs","byte_start":686,"byte_end":718,"line_start":15,"line_end":15,"column_start":1,"column_end":33}},{"value":"!","span":{"file_name":"/Users/icaroferre/.cargo/registry/src/github.com-1ecc6299db9ec823/num-0.1.42/src/lib.rs","byte_start":719,"byte_end":722,"line_start":16,"line_end":16,"column_start":1,"column_end":4}},{"value":"! ## Example","span":{"file_name":"/Users/icaroferre/.cargo/registry/src/github.com-1ecc6299db9ec823/num-0.1.42/src/lib.rs","byte_start":723,"byte_end":737,"line_start":17,"line_end":17,"column_start":1,"column_end":15}},{"value":"!","span":{"file_name":"/Users/icaroferre/.cargo/registry/src/github.com-1ecc6299db9ec823/num-0.1.42/src/lib.rs","byte_start":738,"byte_end":741,"line_start":18,"line_end":18,"column_start":1,"column_end":4}},{"value":"! This example uses the BigRational type and [Newton's method][newt] to","span":{"file_name":"/Users/icaroferre/.cargo/registry/src/github.com-1ecc6299db9ec823/num-0.1.42/src/lib.rs","byte_start":742,"byte_end":815,"line_start":19,"line_end":19,"column_start":1,"column_end":74}},{"value":"! approximate a square root to arbitrary precision:","span":{"file_name":"/Users/icaroferre/.cargo/registry/src/github.com-1ecc6299db9ec823/num-0.1.42/src/lib.rs","byte_start":816,"byte_end":869,"line_start":20,"line_end":20,"column_start":1,"column_end":54}},{"value":"!","span":{"file_name":"/Users/icaroferre/.cargo/registry/src/github.com-1ecc6299db9ec823/num-0.1.42/src/lib.rs","byte_start":870,"byte_end":873,"line_start":21,"line_end":21,"column_start":1,"column_end":4}},{"value":"! ```","span":{"file_name":"/Users/icaroferre/.cargo/registry/src/github.com-1ecc6299db9ec823/num-0.1.42/src/lib.rs","byte_start":874,"byte_end":881,"line_start":22,"line_end":22,"column_start":1,"column_end":8}},{"value":"! extern crate num;","span":{"file_name":"/Users/icaroferre/.cargo/registry/src/github.com-1ecc6299db9ec823/num-0.1.42/src/lib.rs","byte_start":882,"byte_end":903,"line_start":23,"line_end":23,"column_start":1,"column_end":22}},{"value":"! # #[cfg(all(feature = \"bigint\", feature=\"rational\"))]","span":{"file_name":"/Users/icaroferre/.cargo/registry/src/github.com-1ecc6299db9ec823/num-0.1.42/src/lib.rs","byte_start":904,"byte_end":961,"line_start":24,"line_end":24,"column_start":1,"column_end":58}},{"value":"! # mod test {","span":{"file_name":"/Users/icaroferre/.cargo/registry/src/github.com-1ecc6299db9ec823/num-0.1.42/src/lib.rs","byte_start":962,"byte_end":978,"line_start":25,"line_end":25,"column_start":1,"column_end":17}},{"value":"!","span":{"file_name":"/Users/icaroferre/.cargo/registry/src/github.com-1ecc6299db9ec823/num-0.1.42/src/lib.rs","byte_start":979,"byte_end":982,"line_start":26,"line_end":26,"column_start":1,"column_end":4}},{"value":"! use num::FromPrimitive;","span":{"file_name":"/Users/icaroferre/.cargo/registry/src/github.com-1ecc6299db9ec823/num-0.1.42/src/lib.rs","byte_start":983,"byte_end":1010,"line_start":27,"line_end":27,"column_start":1,"column_end":28}},{"value":"! use num::bigint::BigInt;","span":{"file_name":"/Users/icaroferre/.cargo/registry/src/github.com-1ecc6299db9ec823/num-0.1.42/src/lib.rs","byte_start":1011,"byte_end":1039,"line_start":28,"line_end":28,"column_start":1,"column_end":29}},{"value":"! use num::rational::{Ratio, BigRational};","span":{"file_name":"/Users/icaroferre/.cargo/registry/src/github.com-1ecc6299db9ec823/num-0.1.42/src/lib.rs","byte_start":1040,"byte_end":1084,"line_start":29,"line_end":29,"column_start":1,"column_end":45}},{"value":"!","span":{"file_name":"/Users/icaroferre/.cargo/registry/src/github.com-1ecc6299db9ec823/num-0.1.42/src/lib.rs","byte_start":1085,"byte_end":1088,"line_start":30,"line_end":30,"column_start":1,"column_end":4}},{"value":"! # pub","span":{"file_name":"/Users/icaroferre/.cargo/registry/src/github.com-1ecc6299db9ec823/num-0.1.42/src/lib.rs","byte_start":1089,"byte_end":1098,"line_start":31,"line_end":31,"column_start":1,"column_end":10}},{"value":"! fn approx_sqrt(number: u64, iterations: usize) -> BigRational {","span":{"file_name":"/Users/icaroferre/.cargo/registry/src/github.com-1ecc6299db9ec823/num-0.1.42/src/lib.rs","byte_start":1099,"byte_end":1166,"line_start":32,"line_end":32,"column_start":1,"column_end":68}},{"value":"!     let start: Ratio<BigInt> = Ratio::from_integer(FromPrimitive::from_u64(number).unwrap());","span":{"file_name":"/Users/icaroferre/.cargo/registry/src/github.com-1ecc6299db9ec823/num-0.1.42/src/lib.rs","byte_start":1167,"byte_end":1264,"line_start":33,"line_end":33,"column_start":1,"column_end":98}},{"value":"!     let mut approx = start.clone();","span":{"file_name":"/Users/icaroferre/.cargo/registry/src/github.com-1ecc6299db9ec823/num-0.1.42/src/lib.rs","byte_start":1265,"byte_end":1304,"line_start":34,"line_end":34,"column_start":1,"column_end":40}},{"value":"!","span":{"file_name":"/Users/icaroferre/.cargo/registry/src/github.com-1ecc6299db9ec823/num-0.1.42/src/lib.rs","byte_start":1305,"byte_end":1308,"line_start":35,"line_end":35,"column_start":1,"column_end":4}},{"value":"!     for _ in 0..iterations {","span":{"file_name":"/Users/icaroferre/.cargo/registry/src/github.com-1ecc6299db9ec823/num-0.1.42/src/lib.rs","byte_start":1309,"byte_end":1341,"line_start":36,"line_end":36,"column_start":1,"column_end":33}},{"value":"!         approx = (&approx + (&start / &approx)) /","span":{"file_name":"/Users/icaroferre/.cargo/registry/src/github.com-1ecc6299db9ec823/num-0.1.42/src/lib.rs","byte_start":1342,"byte_end":1395,"line_start":37,"line_end":37,"column_start":1,"column_end":54}},{"value":"!             Ratio::from_integer(FromPrimitive::from_u64(2).unwrap());","span":{"file_name":"/Users/icaroferre/.cargo/registry/src/github.com-1ecc6299db9ec823/num-0.1.42/src/lib.rs","byte_start":1396,"byte_end":1469,"line_start":38,"line_end":38,"column_start":1,"column_end":74}},{"value":"!     }","span":{"file_name":"/Users/icaroferre/.cargo/registry/src/github.com-1ecc6299db9ec823/num-0.1.42/src/lib.rs","byte_start":1470,"byte_end":1479,"line_start":39,"line_end":39,"column_start":1,"column_end":10}},{"value":"!","span":{"file_name":"/Users/icaroferre/.cargo/registry/src/github.com-1ecc6299db9ec823/num-0.1.42/src/lib.rs","byte_start":1480,"byte_end":1483,"line_start":40,"line_end":40,"column_start":1,"column_end":4}},{"value":"!     approx","span":{"file_name":"/Users/icaroferre/.cargo/registry/src/github.com-1ecc6299db9ec823/num-0.1.42/src/lib.rs","byte_start":1484,"byte_end":1498,"line_start":41,"line_end":41,"column_start":1,"column_end":15}},{"value":"! }","span":{"file_name":"/Users/icaroferre/.cargo/registry/src/github.com-1ecc6299db9ec823/num-0.1.42/src/lib.rs","byte_start":1499,"byte_end":1504,"line_start":42,"line_end":42,"column_start":1,"column_end":6}},{"value":"! # }","span":{"file_name":"/Users/icaroferre/.cargo/registry/src/github.com-1ecc6299db9ec823/num-0.1.42/src/lib.rs","byte_start":1505,"byte_end":1512,"line_start":43,"line_end":43,"column_start":1,"column_end":8}},{"value":"! # #[cfg(not(all(feature = \"bigint\", feature=\"rational\")))]","span":{"file_name":"/Users/icaroferre/.cargo/registry/src/github.com-1ecc6299db9ec823/num-0.1.42/src/lib.rs","byte_start":1513,"byte_end":1575,"line_start":44,"line_end":44,"column_start":1,"column_end":63}},{"value":"! # mod test { pub fn approx_sqrt(n: u64, _: usize) -> u64 { n } }","span":{"file_name":"/Users/icaroferre/.cargo/registry/src/github.com-1ecc6299db9ec823/num-0.1.42/src/lib.rs","byte_start":1576,"byte_end":1644,"line_start":45,"line_end":45,"column_start":1,"column_end":69}},{"value":"! # use test::approx_sqrt;","span":{"file_name":"/Users/icaroferre/.cargo/registry/src/github.com-1ecc6299db9ec823/num-0.1.42/src/lib.rs","byte_start":1645,"byte_end":1673,"line_start":46,"line_end":46,"column_start":1,"column_end":29}},{"value":"!","span":{"file_name":"/Users/icaroferre/.cargo/registry/src/github.com-1ecc6299db9ec823/num-0.1.42/src/lib.rs","byte_start":1674,"byte_end":1677,"line_start":47,"line_end":47,"column_start":1,"column_end":4}},{"value":"! fn main() {","span":{"file_name":"/Users/icaroferre/.cargo/registry/src/github.com-1ecc6299db9ec823/num-0.1.42/src/lib.rs","byte_start":1678,"byte_end":1693,"line_start":48,"line_end":48,"column_start":1,"column_end":16}},{"value":"!     println!(\"{}\", approx_sqrt(10, 4)); // prints 4057691201/1283082416","span":{"file_name":"/Users/icaroferre/.cargo/registry/src/github.com-1ecc6299db9ec823/num-0.1.42/src/lib.rs","byte_start":1694,"byte_end":1769,"line_start":49,"line_end":49,"column_start":1,"column_end":76}},{"value":"! }","span":{"file_name":"/Users/icaroferre/.cargo/registry/src/github.com-1ecc6299db9ec823/num-0.1.42/src/lib.rs","byte_start":1770,"byte_end":1775,"line_start":50,"line_end":50,"column_start":1,"column_end":6}},{"value":"!","span":{"file_name":"/Users/icaroferre/.cargo/registry/src/github.com-1ecc6299db9ec823/num-0.1.42/src/lib.rs","byte_start":1776,"byte_end":1779,"line_start":51,"line_end":51,"column_start":1,"column_end":4}},{"value":"! ```","span":{"file_name":"/Users/icaroferre/.cargo/registry/src/github.com-1ecc6299db9ec823/num-0.1.42/src/lib.rs","byte_start":1780,"byte_end":1787,"line_start":52,"line_end":52,"column_start":1,"column_end":8}},{"value":"!","span":{"file_name":"/Users/icaroferre/.cargo/registry/src/github.com-1ecc6299db9ec823/num-0.1.42/src/lib.rs","byte_start":1788,"byte_end":1791,"line_start":53,"line_end":53,"column_start":1,"column_end":4}},{"value":"! [newt]: https://en.wikipedia.org/wiki/Methods_of_computing_square_roots#Babylonian_method","span":{"file_name":"/Users/icaroferre/.cargo/registry/src/github.com-1ecc6299db9ec823/num-0.1.42/src/lib.rs","byte_start":1792,"byte_end":1885,"line_start":54,"line_end":54,"column_start":1,"column_end":94}},{"value":"!","span":{"file_name":"/Users/icaroferre/.cargo/registry/src/github.com-1ecc6299db9ec823/num-0.1.42/src/lib.rs","byte_start":1886,"byte_end":1889,"line_start":55,"line_end":55,"column_start":1,"column_end":4}},{"value":"! ## Compatibility","span":{"file_name":"/Users/icaroferre/.cargo/registry/src/github.com-1ecc6299db9ec823/num-0.1.42/src/lib.rs","byte_start":1890,"byte_end":1910,"line_start":56,"line_end":56,"column_start":1,"column_end":21}},{"value":"!","span":{"file_name":"/Users/icaroferre/.cargo/registry/src/github.com-1ecc6299db9ec823/num-0.1.42/src/lib.rs","byte_start":1911,"byte_end":1914,"line_start":57,"line_end":57,"column_start":1,"column_end":4}},{"value":"! The `num` crate is tested for rustc 1.8 and greater.","span":{"file_name":"/Users/icaroferre/.cargo/registry/src/github.com-1ecc6299db9ec823/num-0.1.42/src/lib.rs","byte_start":1915,"byte_end":1971,"line_start":58,"line_end":58,"column_start":1,"column_end":57}}]},{"kind":"Mod","id":{"krate":0,"index":47},"span":{"file_name":"/Users/icaroferre/.cargo/registry/src/github.com-1ecc6299db9ec823/num-0.1.42/src/lib.rs","byte_start":3040,"byte_end":3046,"line_start":89,"line_end":89,"column_start":9,"column_end":15},"name":"bigint","qualname":"::bigint","value":"/Users/icaroferre/.cargo/registry/src/github.com-1ecc6299db9ec823/num-0.1.42/src/lib.rs","parent":null,"children":[{"krate":0,"index":48}],"decl_id":null,"docs":"","sig":null,"attributes":[{"value":"cfg(feature = \"num-bigint\")","span":{"file_name":"/Users/icaroferre/.cargo/registry/src/github.com-1ecc6299db9ec823/num-0.1.42/src/lib.rs","byte_start":3001,"byte_end":3031,"line_start":88,"line_end":88,"column_start":1,"column_end":31}}]},{"kind":"Mod","id":{"krate":0,"index":49},"span":{"file_name":"/Users/icaroferre/.cargo/registry/src/github.com-1ecc6299db9ec823/num-0.1.42/src/lib.rs","byte_start":3119,"byte_end":3126,"line_start":94,"line_end":94,"column_start":9,"column_end":16},"name":"complex","qualname":"::complex","value":"/Users/icaroferre/.cargo/registry/src/github.com-1ecc6299db9ec823/num-0.1.42/src/lib.rs","parent":null,"children":[{"krate":0,"index":50}],"decl_id":null,"docs":"","sig":null,"attributes":[{"value":"cfg(feature = \"num-complex\")","span":{"file_name":"/Users/icaroferre/.cargo/registry/src/github.com-1ecc6299db9ec823/num-0.1.42/src/lib.rs","byte_start":3079,"byte_end":3110,"line_start":93,"line_end":93,"column_start":1,"column_end":32}}]},{"kind":"Mod","id":{"krate":0,"index":51},"span":{"file_name":"/Users/icaroferre/.cargo/registry/src/github.com-1ecc6299db9ec823/num-0.1.42/src/lib.rs","byte_start":3168,"byte_end":3175,"line_start":98,"line_end":98,"column_start":9,"column_end":16},"name":"integer","qualname":"::integer","value":"/Users/icaroferre/.cargo/registry/src/github.com-1ecc6299db9ec823/num-0.1.42/src/lib.rs","parent":null,"children":[{"krate":0,"index":52}],"decl_id":null,"docs":"","sig":null,"attributes":[]},{"kind":"Mod","id":{"krate":0,"index":53},"span":{"file_name":"/Users/icaroferre/.cargo/registry/src/github.com-1ecc6299db9ec823/num-0.1.42/src/lib.rs","byte_start":3217,"byte_end":3221,"line_start":102,"line_end":102,"column_start":9,"column_end":13},"name":"iter","qualname":"::iter","value":"/Users/icaroferre/.cargo/registry/src/github.com-1ecc6299db9ec823/num-0.1.42/src/lib.rs","parent":null,"children":[{"krate":0,"index":54}],"decl_id":null,"docs":"","sig":null,"attributes":[]},{"kind":"Mod","id":{"krate":0,"index":55},"span":{"file_name":"/Users/icaroferre/.cargo/registry/src/github.com-1ecc6299db9ec823/num-0.1.42/src/lib.rs","byte_start":3260,"byte_end":3266,"line_start":106,"line_end":106,"column_start":9,"column_end":15},"name":"traits","qualname":"::traits","value":"/Users/icaroferre/.cargo/registry/src/github.com-1ecc6299db9ec823/num-0.1.42/src/lib.rs","parent":null,"children":[{"krate":0,"index":56}],"decl_id":null,"docs":"","sig":null,"attributes":[]},{"kind":"Mod","id":{"krate":0,"index":57},"span":{"file_name":"/Users/icaroferre/.cargo/registry/src/github.com-1ecc6299db9ec823/num-0.1.42/src/lib.rs","byte_start":3340,"byte_end":3348,"line_start":111,"line_end":111,"column_start":9,"column_end":17},"name":"rational","qualname":"::rational","value":"/Users/icaroferre/.cargo/registry/src/github.com-1ecc6299db9ec823/num-0.1.42/src/lib.rs","parent":null,"children":[{"krate":0,"index":58}],"decl_id":null,"docs":"","sig":null,"attributes":[{"value":"cfg(feature = \"num-rational\")","span":{"file_name":"/Users/icaroferre/.cargo/registry/src/github.com-1ecc6299db9ec823/num-0.1.42/src/lib.rs","byte_start":3299,"byte_end":3331,"line_start":110,"line_end":110,"column_start":1,"column_end":33}}]}],"impls":[],"refs":[],"macro_refs":[],"relations":[]}